Metadata-Version: 2.1
Name: MetaSBT
Version: 0.1.5
Summary: A scalable framework for automatically indexing microbial genomes and accurately characterizing metagenome-assembled genomes with Sequence Bloom Trees
Home-page: http://github.com/cumbof/MetaSBT
Download-URL: https://pypi.org/project/MetaSBT/
Author: Fabio Cumbo
Author-email: fabio.cumbo@gmail.com
License: MIT
Project-URL: Databases, https://github.com/cumbof/MetaSBT-DBs
Project-URL: Discussions, https://github.com/cumbof/MetaSBT/discussions
Project-URL: Issues, https://github.com/cumbof/MetaSBT/issues
Project-URL: Source, https://github.com/cumbof/MetaSBT
Project-URL: Wiki, https://github.com/cumbof/MetaSBT/wiki
Keywords: bioinformatics,characterization,classification,genomes,metagenome-assembled genomes,metagenomics,microbiome,profiling,sequence bloom trees
Platform: Linux
Platform: Mac OSX
Classifier: Environment :: Console
Classifier: Intended Audience :: Science/Research
Classifier: License :: OSI Approved :: MIT License
Classifier: Natural Language :: English
Classifier: Operating System :: POSIX :: Linux
Classifier: Programming Language :: Python :: 3
Classifier: Topic :: Scientific/Engineering :: Bio-Informatics
Requires-Python: >=3.9
License-File: LICENSE
Requires-Dist: biopython>=1.85
Requires-Dist: fastcluster<1.3.0
Requires-Dist: numpy==1.26.4
Requires-Dist: packaging>=25.0
Requires-Dist: requests>=2.32.4
Requires-Dist: scipy>=1.13.1
Requires-Dist: tabulate>=0.9.0
Requires-Dist: tqdm>=4.67.1
